pytdb_cc.cpython-37m-x86_64-linux-gnu.so
pytdb_cc.libs/libprotobuf-79f1ec98.so.25.0.0
pytdb_cc-0.0.7.dist-info/top_level.txt
pytdb_cc-0.0.7.dist-info/WHEEL
pytdb_cc-0.0.7.dist-info/RECORD
pytdb_cc-0.0.7.dist-info/METADATA
